LICENSE
pysslcmz/__init__.py
pysslcmz/_constants.py
pysslcmz/payment.py
pysslcmz-1.1.3.dist-info/LICENSE
pysslcmz-1.1.3.dist-info/METADATA
pysslcmz-1.1.3.dist-info/WHEEL
pysslcmz-1.1.3.dist-info/RECORD
