Metadata-Version: 2.1
Name: pysslcmz
Version: 1.1.3
Summary: Implements SSLCOMMERZ payment gateway in python based web apps (python 3.8+).
Home-page: https://github.com/piecoders/pyssl
License: MIT
Keywords: SSLCommerz,sslcommerz,SSLCOMMERZ,bkash,nagod,upai,rocket
Author: Piecoders IT Solutions
Author-email: piecodersit@gmail.com
Requires-Python: >=3.8,<4.0
Classifier: License :: OSI Approved :: MIT License
Classifier: Operating System :: OS Independent
Classifier: Programming Language :: Python :: 3
Classifier: Programming Language :: Python :: 3.8
Classifier: Programming Language :: Python :: 3.9
Classifier: Programming Language :: Python :: 3.10
Classifier: Programming Language :: Python :: 3.11
Project-URL: Repository, https://github.com/piecoders/pyssl
